yolo_v5_tflite/yolo_v5.py
yolo_v5_tflite-1.0.dist-info/LICENSE
yolo_v5_tflite-1.0.dist-info/METADATA
yolo_v5_tflite-1.0.dist-info/WHEEL
yolo_v5_tflite-1.0.dist-info/top_level.txt
yolo_v5_tflite-1.0.dist-info/RECORD
