Metadata-Version: 2.1
Name: yolo-v5-tflite
Version: 1.0
Summary: YOLO_v5 - most advanced vision AI model for object detection in TFLite. 
Home-page: https://github.com/neso613/yolo-v5-pip-wheel
Author: Neha Soni
Author-email: soni.neha45@gmail.com
License: Apache-2.0
Platform: UNKNOWN
Requires-Python: >=3.5
Requires-Dist: tensorflow (>=2.4.1)
Requires-Dist: numpy (>=1.18.5)
Requires-Dist: opencv-python (>=4.1.2)
Requires-Dist: Pillow
Requires-Dist: PyYAML (>=5.3.1)
Requires-Dist: scipy (>=1.4.1)
Requires-Dist: torchvision (>=0.8.1)
